frproxy/CustomProxy.py
frproxy/__init__.py
frproxy-0.1.3.dist-info/LICENSE
frproxy-0.1.3.dist-info/METADATA
frproxy-0.1.3.dist-info/WHEEL
frproxy-0.1.3.dist-info/top_level.txt
frproxy-0.1.3.dist-info/RECORD
