Metadata-Version: 2.1
Name: frproxy
Version: 0.1.3
Summary: free rotation proxy
Home-page: https://github.com/pypa/sampleproject
Author: ta27
Author-email: tarangga.code@gmail.com
License: UNKNOWN
Project-URL: Bug Tracker, https://github.com/pypa/sampleproject/issues
Platform: UNKNOWN
Classifier: Programming Language :: Python :: 3
Classifier: License :: OSI Approved :: MIT License
Classifier: Operating System :: OS Independent
Requires-Python: >=3.6
License-File: LICENSE
